pcm_player/__init__.py
pcm_player/__main__.py
pcm_player/player.py
pcm_player/version.py
pcm_player-0.3.1.dist-info/LICENSE
pcm_player-0.3.1.dist-info/METADATA
pcm_player-0.3.1.dist-info/WHEEL
pcm_player-0.3.1.dist-info/entry_points.txt
pcm_player-0.3.1.dist-info/RECORD
